scikit_chainer-0.4.2.dist-info/DESCRIPTION.rst
scikit_chainer-0.4.2.dist-info/METADATA
scikit_chainer-0.4.2.dist-info/RECORD
scikit_chainer-0.4.2.dist-info/WHEEL
scikit_chainer-0.4.2.dist-info/metadata.json
scikit_chainer-0.4.2.dist-info/top_level.txt
skchainer/__init__.py
skchainer/autoencoder.py
skchainer/linear.py
skchainer/mlp.py
