Metadata-Version: 2.0
Name: scikit-chainer
Version: 0.4.2
Summary: scikit-learn like interface for chainer
Home-page: https://github.com/lucidfrontier45/scikit-chainer
Author: Shiqiao Du
Author-email: lucidfrontier.45@gmail.com
License: MIT
Platform: UNKNOWN
Classifier: Development Status :: 3 - Alpha
Classifier: License :: OSI Approved :: MIT License
Classifier: Intended Audience :: Science/Research
Classifier: Programming Language :: Python
Classifier: Topic :: Scientific/Engineering :: Artificial Intelligence
Requires-Dist: chainer (>=1.5.1)
Requires-Dist: scikit-learn
